{"frames": [{"objects": [{"position": [115, 15, 121, 19], "class": "fish", "colour": "silver", "rotation": 3}, {"position": [48, 48, 52, 54], "class": "fish", "colour": "silver", "rotation": 2}, {"position": [43, 108, 49, 112], "class": "fish", "colour": "silver", "rotation": 3}, {"position": [76, 84, 80, 90], "class": "bag", "colour": "white", "rotation": 0}, {"position": [44, 18, 50, 22], "class": "bag", "colour": "white", "rotation": 1}, {"position": [82, 10, 88, 16], "class": "rock", "colour": "blue", "rotation": 0}, {"position": [109, 109, 115, 115], "class": "rock", "colour": "green", "rotation": 0}, {"position": [112, 77, 118, 83], "class": "rock", "colour": "brown", "rotation": 0}, {"position": [82, 38, 92, 48], "class": "octopus", "colour": "red", "rotation": 0}]}, {"objects": [{"position": [115, 15, 121, 19], "class": "fish", "colour": "silver", "rotation": 3}, {"position": [48, 48, 52, 54], "class": "fish", "colour": "silver", "rotation": 2}, {"position": [43, 108, 49, 112], "class": "fish", "colour": "silver", "rotation": 3}, {"position": [76, 84, 80, 90], "class": "bag", "colour": "white", "rotation": 0}, {"position": [44, 18, 50, 22], "class": "bag", "colour": "white", "rotation": 1}, {"position": [82, 10, 88, 16], "class": "rock", "colour": "blue", "rotation": 0}, {"position": [109, 109, 115, 115], "class": "rock", "colour": "green", "rotation": 0}, {"position": [112, 77, 118, 83], "class": "rock", "colour": "brown", "rotation": 0}, {"position": [82, 26, 92, 36], "class": "octopus", "colour": "red", "rotation": 0}]}, {"objects": [{"position": [115, 15, 121, 19], "class": "fish", "colour": "silver", "rotation": 3}, {"position": [48, 48, 52, 54], "class": "fish", "colour": "silver", "rotation": 2}, {"position": [43, 108, 49, 112], "class": "fish", "colour": "silver", "rotation": 3}, {"position": [76, 84, 80, 90], "class": "bag", "colour": "white", "rotation": 0}, {"position": [44, 18, 50, 22], "class": "bag", "colour": "white", "rotation": 1}, {"position": [82, 10, 88, 16], "class": "rock", "colour": "blue", "rotation": 0}, {"position": [109, 109, 115, 115], "class": "rock", "colour": "green", "rotation": 0}, {"position": [112, 77, 118, 83], "class": "rock", "colour": "brown", "rotation": 0}, {"position": [82, 14, 92, 24], "class": "octopus", "colour": "blue", "rotation": 0}]}, {"objects": [{"position": [115, 15, 121, 19], "class": "fish", "colour": "silver", "rotation": 3}, {"position": [48, 48, 52, 54], "class": "fish", "colour": "silver", "rotation": 2}, {"position": [43, 108, 49, 112], "class": "fish", "colour": "silver", "rotation": 3}, {"position": [76, 84, 80, 90], "class": "bag", "colour": "white", "rotation": 0}, {"position": [44, 18, 50, 22], "class": "bag", "colour": "white", "rotation": 1}, {"position": [82, 10, 88, 16], "class": "rock", "colour": "blue", "rotation": 0}, {"position": [109, 109, 115, 115], "class": "rock", "colour": "green", "rotation": 0}, {"position": [112, 77, 118, 83], "class": "rock", "colour": "brown", "rotation": 0}, {"position": [82, 2, 92, 12], "class": "octopus", "colour": "blue", "rotation": 0}]}, {"objects": [{"position": [115, 15, 121, 19], "class": "fish", "colour": "silver", "rotation": 3}, {"position": [48, 48, 52, 54], "class": "fish", "colour": "silver", "rotation": 2}, {"position": [43, 108, 49, 112], "class": "fish", "colour": "silver", "rotation": 3}, {"position": [76, 84, 80, 90], "class": "bag", "colour": "white", "rotation": 0}, {"position": [44, 18, 50, 22], "class": "bag", "colour": "white", "rotation": 1}, {"position": [82, 10, 88, 16], "class": "rock", "colour": "blue", "rotation": 0}, {"position": [109, 109, 115, 115], "class": "rock", "colour": "green", "rotation": 0}, {"position": [112, 77, 118, 83], "class": "rock", "colour": "brown", "rotation": 0}, {"position": [82, 2, 92, 12], "class": "octopus", "colour": "blue", "rotation": 1}]}, {"objects": [{"position": [115, 15, 121, 19], "class": "fish", "colour": "silver", "rotation": 3}, {"position": [48, 48, 52, 54], "class": "fish", "colour": "silver", "rotation": 2}, {"position": [43, 108, 49, 112], "class": "fish", "colour": "silver", "rotation": 3}, {"position": [76, 84, 80, 90], "class": "bag", "colour": "white", "rotation": 0}, {"position": [44, 18, 50, 22], "class": "bag", "colour": "white", "rotation": 1}, {"position": [82, 10, 88, 16], "class": "rock", "colour": "blue", "rotation": 0}, {"position": [109, 109, 115, 115], "class": "rock", "colour": "green", "rotation": 0}, {"position": [112, 77, 118, 83], "class": "rock", "colour": "brown", "rotation": 0}, {"position": [82, 2, 92, 12], "class": "octopus", "colour": "blue", "rotation": 2}]}, {"objects": [{"position": [115, 15, 121, 19], "class": "fish", "colour": "silver", "rotation": 3}, {"position": [48, 48, 52, 54], "class": "fish", "colour": "silver", "rotation": 2}, {"position": [43, 108, 49, 112], "class": "fish", "colour": "silver", "rotation": 3}, {"position": [76, 84, 80, 90], "class": "bag", "colour": "white", "rotation": 0}, {"position": [44, 18, 50, 22], "class": "bag", "colour": "white", "rotation": 1}, {"position": [82, 10, 88, 16], "class": "rock", "colour": "blue", "rotation": 0}, {"position": [109, 109, 115, 115], "class": "rock", "colour": "green", "rotation": 0}, {"position": [112, 77, 118, 83], "class": "rock", "colour": "brown", "rotation": 0}, {"position": [82, 14, 92, 24], "class": "octopus", "colour": "blue", "rotation": 2}]}, {"objects": [{"position": [115, 15, 121, 19], "class": "fish", "colour": "silver", "rotation": 3}, {"position": [48, 48, 52, 54], "class": "fish", "colour": "silver", "rotation": 2}, {"position": [43, 108, 49, 112], "class": "fish", "colour": "silver", "rotation": 3}, {"position": [76, 84, 80, 90], "class": "bag", "colour": "white", "rotation": 0}, {"position": [44, 18, 50, 22], "class": "bag", "colour": "white", "rotation": 1}, {"position": [82, 10, 88, 16], "class": "rock", "colour": "blue", "rotation": 0}, {"position": [109, 109, 115, 115], "class": "rock", "colour": "green", "rotation": 0}, {"position": [112, 77, 118, 83], "class": "rock", "colour": "brown", "rotation": 0}, {"position": [82, 26, 92, 36], "class": "octopus", "colour": "blue", "rotation": 2}]}, {"objects": [{"position": [115, 15, 121, 19], "class": "fish", "colour": "silver", "rotation": 3}, {"position": [48, 48, 52, 54], "class": "fish", "colour": "silver", "rotation": 2}, {"position": [43, 108, 49, 112], "class": "fish", "colour": "silver", "rotation": 3}, {"position": [76, 84, 80, 90], "class": "bag", "colour": "white", "rotation": 0}, {"position": [44, 18, 50, 22], "class": "bag", "colour": "white", "rotation": 1}, {"position": [82, 10, 88, 16], "class": "rock", "colour": "blue", "rotation": 0}, {"position": [109, 109, 115, 115], "class": "rock", "colour": "green", "rotation": 0}, {"position": [112, 77, 118, 83], "class": "rock", "colour": "brown", "rotation": 0}, {"position": [82, 38, 92, 48], "class": "octopus", "colour": "blue", "rotation": 2}]}, {"objects": [{"position": [115, 15, 121, 19], "class": "fish", "colour": "silver", "rotation": 3}, {"position": [48, 48, 52, 54], "class": "fish", "colour": "silver", "rotation": 2}, {"position": [43, 108, 49, 112], "class": "fish", "colour": "silver", "rotation": 3}, {"position": [76, 84, 80, 90], "class": "bag", "colour": "white", "rotation": 0}, {"position": [44, 18, 50, 22], "class": "bag", "colour": "white", "rotation": 1}, {"position": [82, 10, 88, 16], "class": "rock", "colour": "blue", "rotation": 0}, {"position": [109, 109, 115, 115], "class": "rock", "colour": "green", "rotation": 0}, {"position": [112, 77, 118, 83], "class": "rock", "colour": "brown", "rotation": 0}, {"position": [82, 50, 92, 60], "class": "octopus", "colour": "blue", "rotation": 2}]}, {"objects": [{"position": [115, 15, 121, 19], "class": "fish", "colour": "silver", "rotation": 3}, {"position": [48, 48, 52, 54], "class": "fish", "colour": "silver", "rotation": 2}, {"position": [43, 108, 49, 112], "class": "fish", "colour": "silver", "rotation": 3}, {"position": [76, 84, 80, 90], "class": "bag", "colour": "white", "rotation": 0}, {"position": [44, 18, 50, 22], "class": "bag", "colour": "white", "rotation": 1}, {"position": [82, 10, 88, 16], "class": "rock", "colour": "blue", "rotation": 0}, {"position": [109, 109, 115, 115], "class": "rock", "colour": "green", "rotation": 0}, {"position": [112, 77, 118, 83], "class": "rock", "colour": "brown", "rotation": 0}, {"position": [82, 62, 92, 72], "class": "octopus", "colour": "blue", "rotation": 2}]}, {"objects": [{"position": [115, 15, 121, 19], "class": "fish", "colour": "silver", "rotation": 3}, {"position": [48, 48, 52, 54], "class": "fish", "colour": "silver", "rotation": 2}, {"position": [43, 108, 49, 112], "class": "fish", "colour": "silver", "rotation": 3}, {"position": [76, 84, 80, 90], "class": "bag", "colour": "white", "rotation": 0}, {"position": [44, 18, 50, 22], "class": "bag", "colour": "white", "rotation": 1}, {"position": [82, 10, 88, 16], "class": "rock", "colour": "blue", "rotation": 0}, {"position": [109, 109, 115, 115], "class": "rock", "colour": "green", "rotation": 0}, {"position": [112, 77, 118, 83], "class": "rock", "colour": "brown", "rotation": 0}, {"position": [82, 62, 92, 72], "class": "octopus", "colour": "blue", "rotation": 1}]}, {"objects": [{"position": [115, 15, 121, 19], "class": "fish", "colour": "silver", "rotation": 3}, {"position": [48, 48, 52, 54], "class": "fish", "colour": "silver", "rotation": 2}, {"position": [43, 108, 49, 112], "class": "fish", "colour": "silver", "rotation": 3}, {"position": [76, 84, 80, 90], "class": "bag", "colour": "white", "rotation": 0}, {"position": [44, 18, 50, 22], "class": "bag", "colour": "white", "rotation": 1}, {"position": [82, 10, 88, 16], "class": "rock", "colour": "blue", "rotation": 0}, {"position": [109, 109, 115, 115], "class": "rock", "colour": "green", "rotation": 0}, {"position": [112, 77, 118, 83], "class": "rock", "colour": "brown", "rotation": 0}, {"position": [94, 62, 104, 72], "class": "octopus", "colour": "blue", "rotation": 1}]}, {"objects": [{"position": [115, 15, 121, 19], "class": "fish", "colour": "silver", "rotation": 3}, {"position": [48, 48, 52, 54], "class": "fish", "colour": "silver", "rotation": 2}, {"position": [43, 108, 49, 112], "class": "fish", "colour": "silver", "rotation": 3}, {"position": [76, 84, 80, 90], "class": "bag", "colour": "white", "rotation": 0}, {"position": [44, 18, 50, 22], "class": "bag", "colour": "white", "rotation": 1}, {"position": [82, 10, 88, 16], "class": "rock", "colour": "blue", "rotation": 0}, {"position": [109, 109, 115, 115], "class": "rock", "colour": "green", "rotation": 0}, {"position": [112, 77, 118, 83], "class": "rock", "colour": "brown", "rotation": 0}, {"position": [106, 62, 116, 72], "class": "octopus", "colour": "brown", "rotation": 1}]}, {"objects": [{"position": [115, 15, 121, 19], "class": "fish", "colour": "silver", "rotation": 3}, {"position": [48, 48, 52, 54], "class": "fish", "colour": "silver", "rotation": 2}, {"position": [43, 108, 49, 112], "class": "fish", "colour": "silver", "rotation": 3}, {"position": [76, 84, 80, 90], "class": "bag", "colour": "white", "rotation": 0}, {"position": [44, 18, 50, 22], "class": "bag", "colour": "white", "rotation": 1}, {"position": [82, 10, 88, 16], "class": "rock", "colour": "blue", "rotation": 0}, {"position": [109, 109, 115, 115], "class": "rock", "colour": "green", "rotation": 0}, {"position": [112, 77, 118, 83], "class": "rock", "colour": "brown", "rotation": 0}, {"position": [106, 62, 116, 72], "class": "octopus", "colour": "brown", "rotation": 0}]}, {"objects": [{"position": [115, 15, 121, 19], "class": "fish", "colour": "silver", "rotation": 3}, {"position": [48, 48, 52, 54], "class": "fish", "colour": "silver", "rotation": 2}, {"position": [43, 108, 49, 112], "class": "fish", "colour": "silver", "rotation": 3}, {"position": [76, 84, 80, 90], "class": "bag", "colour": "white", "rotation": 0}, {"position": [44, 18, 50, 22], "class": "bag", "colour": "white", "rotation": 1}, {"position": [82, 10, 88, 16], "class": "rock", "colour": "blue", "rotation": 0}, {"position": [109, 109, 115, 115], "class": "rock", "colour": "green", "rotation": 0}, {"position": [112, 77, 118, 83], "class": "rock", "colour": "brown", "rotation": 0}, {"position": [106, 62, 116, 72], "class": "octopus", "colour": "brown", "rotation": 3}]}, {"objects": [{"position": [115, 15, 121, 19], "class": "fish", "colour": "silver", "rotation": 3}, {"position": [48, 48, 52, 54], "class": "fish", "colour": "silver", "rotation": 2}, {"position": [43, 108, 49, 112], "class": "fish", "colour": "silver", "rotation": 3}, {"position": [76, 84, 80, 90], "class": "bag", "colour": "white", "rotation": 0}, {"position": [44, 18, 50, 22], "class": "bag", "colour": "white", "rotation": 1}, {"position": [82, 10, 88, 16], "class": "rock", "colour": "blue", "rotation": 0}, {"position": [109, 109, 115, 115], "class": "rock", "colour": "green", "rotation": 0}, {"position": [112, 77, 118, 83], "class": "rock", "colour": "brown", "rotation": 0}, {"position": [106, 62, 116, 72], "class": "octopus", "colour": "brown", "rotation": 2}]}, {"objects": [{"position": [115, 15, 121, 19], "class": "fish", "colour": "silver", "rotation": 3}, {"position": [48, 48, 52, 54], "class": "fish", "colour": "silver", "rotation": 2}, {"position": [43, 108, 49, 112], "class": "fish", "colour": "silver", "rotation": 3}, {"position": [76, 84, 80, 90], "class": "bag", "colour": "white", "rotation": 0}, {"position": [44, 18, 50, 22], "class": "bag", "colour": "white", "rotation": 1}, {"position": [82, 10, 88, 16], "class": "rock", "colour": "blue", "rotation": 0}, {"position": [109, 109, 115, 115], "class": "rock", "colour": "green", "rotation": 0}, {"position": [112, 77, 118, 83], "class": "rock", "colour": "brown", "rotation": 0}, {"position": [106, 74, 116, 84], "class": "octopus", "colour": "brown", "rotation": 2}]}, {"objects": [{"position": [115, 15, 121, 19], "class": "fish", "colour": "silver", "rotation": 3}, {"position": [48, 48, 52, 54], "class": "fish", "colour": "silver", "rotation": 2}, {"position": [43, 108, 49, 112], "class": "fish", "colour": "silver", "rotation": 3}, {"position": [76, 84, 80, 90], "class": "bag", "colour": "white", "rotation": 0}, {"position": [44, 18, 50, 22], "class": "bag", "colour": "white", "rotation": 1}, {"position": [82, 10, 88, 16], "class": "rock", "colour": "blue", "rotation": 0}, {"position": [109, 109, 115, 115], "class": "rock", "colour": "green", "rotation": 0}, {"position": [112, 77, 118, 83], "class": "rock", "colour": "brown", "rotation": 0}, {"position": [106, 86, 116, 96], "class": "octopus", "colour": "brown", "rotation": 2}]}, {"objects": [{"position": [115, 15, 121, 19], "class": "fish", "colour": "silver", "rotation": 3}, {"position": [48, 48, 52, 54], "class": "fish", "colour": "silver", "rotation": 2}, {"position": [43, 108, 49, 112], "class": "fish", "colour": "silver", "rotation": 3}, {"position": [76, 84, 80, 90], "class": "bag", "colour": "white", "rotation": 0}, {"position": [44, 18, 50, 22], "class": "bag", "colour": "white", "rotation": 1}, {"position": [82, 10, 88, 16], "class": "rock", "colour": "blue", "rotation": 0}, {"position": [109, 109, 115, 115], "class": "rock", "colour": "green", "rotation": 0}, {"position": [112, 77, 118, 83], "class": "rock", "colour": "brown", "rotation": 0}, {"position": [106, 98, 116, 108], "class": "octopus", "colour": "green", "rotation": 2}]}, {"objects": [{"position": [115, 15, 121, 19], "class": "fish", "colour": "silver", "rotation": 3}, {"position": [48, 48, 52, 54], "class": "fish", "colour": "silver", "rotation": 2}, {"position": [43, 108, 49, 112], "class": "fish", "colour": "silver", "rotation": 3}, {"position": [76, 84, 80, 90], "class": "bag", "colour": "white", "rotation": 0}, {"position": [44, 18, 50, 22], "class": "bag", "colour": "white", "rotation": 1}, {"position": [82, 10, 88, 16], "class": "rock", "colour": "blue", "rotation": 0}, {"position": [109, 109, 115, 115], "class": "rock", "colour": "green", "rotation": 0}, {"position": [112, 77, 118, 83], "class": "rock", "colour": "brown", "rotation": 0}, {"position": [106, 110, 116, 120], "class": "octopus", "colour": "green", "rotation": 2}]}, {"objects": [{"position": [115, 15, 121, 19], "class": "fish", "colour": "silver", "rotation": 3}, {"position": [48, 48, 52, 54], "class": "fish", "colour": "silver", "rotation": 2}, {"position": [43, 108, 49, 112], "class": "fish", "colour": "silver", "rotation": 3}, {"position": [76, 84, 80, 90], "class": "bag", "colour": "white", "rotation": 0}, {"position": [44, 18, 50, 22], "class": "bag", "colour": "white", "rotation": 1}, {"position": [82, 10, 88, 16], "class": "rock", "colour": "blue", "rotation": 0}, {"position": [109, 109, 115, 115], "class": "rock", "colour": "green", "rotation": 0}, {"position": [112, 77, 118, 83], "class": "rock", "colour": "brown", "rotation": 0}, {"position": [106, 110, 116, 120], "class": "octopus", "colour": "green", "rotation": 1}]}, {"objects": [{"position": [115, 15, 121, 19], "class": "fish", "colour": "silver", "rotation": 3}, {"position": [48, 48, 52, 54], "class": "fish", "colour": "silver", "rotation": 2}, {"position": [43, 108, 49, 112], "class": "fish", "colour": "silver", "rotation": 3}, {"position": [76, 84, 80, 90], "class": "bag", "colour": "white", "rotation": 0}, {"position": [44, 18, 50, 22], "class": "bag", "colour": "white", "rotation": 1}, {"position": [82, 10, 88, 16], "class": "rock", "colour": "blue", "rotation": 0}, {"position": [109, 109, 115, 115], "class": "rock", "colour": "green", "rotation": 0}, {"position": [112, 77, 118, 83], "class": "rock", "colour": "brown", "rotation": 0}, {"position": [106, 110, 116, 120], "class": "octopus", "colour": "green", "rotation": 2}]}, {"objects": [{"position": [115, 15, 121, 19], "class": "fish", "colour": "silver", "rotation": 3}, {"position": [48, 48, 52, 54], "class": "fish", "colour": "silver", "rotation": 2}, {"position": [43, 108, 49, 112], "class": "fish", "colour": "silver", "rotation": 3}, {"position": [76, 84, 80, 90], "class": "bag", "colour": "white", "rotation": 0}, {"position": [44, 18, 50, 22], "class": "bag", "colour": "white", "rotation": 1}, {"position": [82, 10, 88, 16], "class": "rock", "colour": "blue", "rotation": 0}, {"position": [109, 109, 115, 115], "class": "rock", "colour": "green", "rotation": 0}, {"position": [112, 77, 118, 83], "class": "rock", "colour": "brown", "rotation": 0}, {"position": [106, 110, 116, 120], "class": "octopus", "colour": "green", "rotation": 3}]}, {"objects": [{"position": [115, 15, 121, 19], "class": "fish", "colour": "silver", "rotation": 3}, {"position": [48, 48, 52, 54], "class": "fish", "colour": "silver", "rotation": 2}, {"position": [43, 108, 49, 112], "class": "fish", "colour": "silver", "rotation": 3}, {"position": [76, 84, 80, 90], "class": "bag", "colour": "white", "rotation": 0}, {"position": [44, 18, 50, 22], "class": "bag", "colour": "white", "rotation": 1}, {"position": [82, 10, 88, 16], "class": "rock", "colour": "blue", "rotation": 0}, {"position": [109, 109, 115, 115], "class": "rock", "colour": "green", "rotation": 0}, {"position": [112, 77, 118, 83], "class": "rock", "colour": "brown", "rotation": 0}, {"position": [106, 110, 116, 120], "class": "octopus", "colour": "green", "rotation": 0}]}, {"objects": [{"position": [115, 15, 121, 19], "class": "fish", "colour": "silver", "rotation": 3}, {"position": [48, 48, 52, 54], "class": "fish", "colour": "silver", "rotation": 2}, {"position": [43, 108, 49, 112], "class": "fish", "colour": "silver", "rotation": 3}, {"position": [76, 84, 80, 90], "class": "bag", "colour": "white", "rotation": 0}, {"position": [44, 18, 50, 22], "class": "bag", "colour": "white", "rotation": 1}, {"position": [82, 10, 88, 16], "class": "rock", "colour": "blue", "rotation": 0}, {"position": [109, 109, 115, 115], "class": "rock", "colour": "green", "rotation": 0}, {"position": [112, 77, 118, 83], "class": "rock", "colour": "brown", "rotation": 0}, {"position": [106, 98, 116, 108], "class": "octopus", "colour": "green", "rotation": 0}]}, {"objects": [{"position": [115, 15, 121, 19], "class": "fish", "colour": "silver", "rotation": 3}, {"position": [48, 48, 52, 54], "class": "fish", "colour": "silver", "rotation": 2}, {"position": [43, 108, 49, 112], "class": "fish", "colour": "silver", "rotation": 3}, {"position": [76, 84, 80, 90], "class": "bag", "colour": "white", "rotation": 0}, {"position": [44, 18, 50, 22], "class": "bag", "colour": "white", "rotation": 1}, {"position": [82, 10, 88, 16], "class": "rock", "colour": "blue", "rotation": 0}, {"position": [109, 109, 115, 115], "class": "rock", "colour": "green", "rotation": 0}, {"position": [112, 77, 118, 83], "class": "rock", "colour": "brown", "rotation": 0}, {"position": [106, 86, 116, 96], "class": "octopus", "colour": "brown", "rotation": 0}]}, {"objects": [{"position": [115, 15, 121, 19], "class": "fish", "colour": "silver", "rotation": 3}, {"position": [48, 48, 52, 54], "class": "fish", "colour": "silver", "rotation": 2}, {"position": [43, 108, 49, 112], "class": "fish", "colour": "silver", "rotation": 3}, {"position": [76, 84, 80, 90], "class": "bag", "colour": "white", "rotation": 0}, {"position": [44, 18, 50, 22], "class": "bag", "colour": "white", "rotation": 1}, {"position": [82, 10, 88, 16], "class": "rock", "colour": "blue", "rotation": 0}, {"position": [109, 109, 115, 115], "class": "rock", "colour": "green", "rotation": 0}, {"position": [112, 77, 118, 83], "class": "rock", "colour": "brown", "rotation": 0}, {"position": [106, 86, 116, 96], "class": "octopus", "colour": "brown", "rotation": 3}]}, {"objects": [{"position": [115, 15, 121, 19], "class": "fish", "colour": "silver", "rotation": 3}, {"position": [48, 48, 52, 54], "class": "fish", "colour": "silver", "rotation": 2}, {"position": [43, 108, 49, 112], "class": "fish", "colour": "silver", "rotation": 3}, {"position": [76, 84, 80, 90], "class": "bag", "colour": "white", "rotation": 0}, {"position": [44, 18, 50, 22], "class": "bag", "colour": "white", "rotation": 1}, {"position": [82, 10, 88, 16], "class": "rock", "colour": "blue", "rotation": 0}, {"position": [109, 109, 115, 115], "class": "rock", "colour": "green", "rotation": 0}, {"position": [112, 77, 118, 83], "class": "rock", "colour": "brown", "rotation": 0}, {"position": [94, 86, 104, 96], "class": "octopus", "colour": "brown", "rotation": 3}]}, {"objects": [{"position": [115, 15, 121, 19], "class": "fish", "colour": "silver", "rotation": 3}, {"position": [48, 48, 52, 54], "class": "fish", "colour": "silver", "rotation": 2}, {"position": [43, 108, 49, 112], "class": "fish", "colour": "silver", "rotation": 3}, {"position": [76, 84, 80, 90], "class": "bag", "colour": "white", "rotation": 0}, {"position": [44, 18, 50, 22], "class": "bag", "colour": "white", "rotation": 1}, {"position": [82, 10, 88, 16], "class": "rock", "colour": "blue", "rotation": 0}, {"position": [109, 109, 115, 115], "class": "rock", "colour": "green", "rotation": 0}, {"position": [112, 77, 118, 83], "class": "rock", "colour": "brown", "rotation": 0}, {"position": [94, 86, 104, 96], "class": "octopus", "colour": "brown", "rotation": 2}]}, {"objects": [{"position": [115, 15, 121, 19], "class": "fish", "colour": "silver", "rotation": 3}, {"position": [48, 48, 52, 54], "class": "fish", "colour": "silver", "rotation": 2}, {"position": [43, 108, 49, 112], "class": "fish", "colour": "silver", "rotation": 3}, {"position": [76, 84, 80, 90], "class": "bag", "colour": "white", "rotation": 0}, {"position": [44, 18, 50, 22], "class": "bag", "colour": "white", "rotation": 1}, {"position": [82, 10, 88, 16], "class": "rock", "colour": "blue", "rotation": 0}, {"position": [109, 109, 115, 115], "class": "rock", "colour": "green", "rotation": 0}, {"position": [112, 77, 118, 83], "class": "rock", "colour": "brown", "rotation": 0}, {"position": [94, 98, 104, 108], "class": "octopus", "colour": "green", "rotation": 2}]}, {"objects": [{"position": [115, 15, 121, 19], "class": "fish", "colour": "silver", "rotation": 3}, {"position": [48, 48, 52, 54], "class": "fish", "colour": "silver", "rotation": 2}, {"position": [43, 108, 49, 112], "class": "fish", "colour": "silver", "rotation": 3}, {"position": [76, 84, 80, 90], "class": "bag", "colour": "white", "rotation": 0}, {"position": [44, 18, 50, 22], "class": "bag", "colour": "white", "rotation": 1}, {"position": [82, 10, 88, 16], "class": "rock", "colour": "blue", "rotation": 0}, {"position": [109, 109, 115, 115], "class": "rock", "colour": "green", "rotation": 0}, {"position": [112, 77, 118, 83], "class": "rock", "colour": "brown", "rotation": 0}, {"position": [94, 98, 104, 108], "class": "octopus", "colour": "green", "rotation": 1}]}], "events": [["move"], ["colour change", "move"], ["colour change", "move"], ["colour change", "rotate"], ["colour change", "rotate"], ["colour change", "move"], ["move"], ["move"], ["move"], ["move"], ["rotate"], ["move"], ["colour change", "move"], ["colour change", "rotate"], ["colour change", "rotate"], ["colour change", "rotate"], ["colour change", "move"], ["colour change", "move"], ["colour change", "move"], ["colour change", "move"], ["colour change", "rotate"], ["colour change", "rotate"], ["colour change", "rotate"], ["colour change", "rotate"], ["colour change", "move"], ["colour change", "move"], ["colour change", "rotate"], ["move"], ["rotate"], ["colour change", "move"], ["colour change", "rotate"]]}