{"frames": [{"objects": [{"position": [109, 101, 113, 107], "class": "fish", "colour": "silver", "rotation": 0}, {"position": [35, 118, 39, 124], "class": "fish", "colour": "silver", "rotation": 0}, {"position": [49, 70, 53, 76], "class": "fish", "colour": "silver", "rotation": 2}, {"position": [68, 86, 74, 90], "class": "fish", "colour": "silver", "rotation": 1}, {"position": [100, 79, 106, 83], "class": "bag", "colour": "white", "rotation": 3}, {"position": [70, 45, 76, 49], "class": "bag", "colour": "white", "rotation": 3}, {"position": [18, 39, 24, 43], "class": "bag", "colour": "white", "rotation": 1}, {"position": [5, 114, 9, 120], "class": "bag", "colour": "white", "rotation": 0}, {"position": [36, 10, 42, 16], "class": "rock", "colour": "purple", "rotation": 0}, {"position": [4, 70, 10, 76], "class": "rock", "colour": "purple", "rotation": 0}, {"position": [80, 101, 86, 107], "class": "rock", "colour": "blue", "rotation": 0}, {"position": [103, 43, 113, 53], "class": "octopus", "colour": "red", "rotation": 1}]}, {"objects": [{"position": [109, 101, 113, 107], "class": "fish", "colour": "silver", "rotation": 0}, {"position": [35, 118, 39, 124], "class": "fish", "colour": "silver", "rotation": 0}, {"position": [49, 70, 53, 76], "class": "fish", "colour": "silver", "rotation": 2}, {"position": [68, 86, 74, 90], "class": "fish", "colour": "silver", "rotation": 1}, {"position": [100, 79, 106, 83], "class": "bag", "colour": "white", "rotation": 3}, {"position": [70, 45, 76, 49], "class": "bag", "colour": "white", "rotation": 3}, {"position": [18, 39, 24, 43], "class": "bag", "colour": "white", "rotation": 1}, {"position": [5, 114, 9, 120], "class": "bag", "colour": "white", "rotation": 0}, {"position": [36, 10, 42, 16], "class": "rock", "colour": "purple", "rotation": 0}, {"position": [4, 70, 10, 76], "class": "rock", "colour": "purple", "rotation": 0}, {"position": [80, 101, 86, 107], "class": "rock", "colour": "blue", "rotation": 0}, {"position": [115, 43, 125, 53], "class": "octopus", "colour": "red", "rotation": 1}]}, {"objects": [{"position": [109, 101, 113, 107], "class": "fish", "colour": "silver", "rotation": 0}, {"position": [35, 118, 39, 124], "class": "fish", "colour": "silver", "rotation": 0}, {"position": [49, 70, 53, 76], "class": "fish", "colour": "silver", "rotation": 2}, {"position": [68, 86, 74, 90], "class": "fish", "colour": "silver", "rotation": 1}, {"position": [100, 79, 106, 83], "class": "bag", "colour": "white", "rotation": 3}, {"position": [70, 45, 76, 49], "class": "bag", "colour": "white", "rotation": 3}, {"position": [18, 39, 24, 43], "class": "bag", "colour": "white", "rotation": 1}, {"position": [5, 114, 9, 120], "class": "bag", "colour": "white", "rotation": 0}, {"position": [36, 10, 42, 16], "class": "rock", "colour": "purple", "rotation": 0}, {"position": [4, 70, 10, 76], "class": "rock", "colour": "purple", "rotation": 0}, {"position": [80, 101, 86, 107], "class": "rock", "colour": "blue", "rotation": 0}, {"position": [115, 43, 125, 53], "class": "octopus", "colour": "red", "rotation": 2}]}, {"objects": [{"position": [109, 101, 113, 107], "class": "fish", "colour": "silver", "rotation": 0}, {"position": [35, 118, 39, 124], "class": "fish", "colour": "silver", "rotation": 0}, {"position": [49, 70, 53, 76], "class": "fish", "colour": "silver", "rotation": 2}, {"position": [68, 86, 74, 90], "class": "fish", "colour": "silver", "rotation": 1}, {"position": [100, 79, 106, 83], "class": "bag", "colour": "white", "rotation": 3}, {"position": [70, 45, 76, 49], "class": "bag", "colour": "white", "rotation": 3}, {"position": [18, 39, 24, 43], "class": "bag", "colour": "white", "rotation": 1}, {"position": [5, 114, 9, 120], "class": "bag", "colour": "white", "rotation": 0}, {"position": [36, 10, 42, 16], "class": "rock", "colour": "purple", "rotation": 0}, {"position": [4, 70, 10, 76], "class": "rock", "colour": "purple", "rotation": 0}, {"position": [80, 101, 86, 107], "class": "rock", "colour": "blue", "rotation": 0}, {"position": [115, 43, 125, 53], "class": "octopus", "colour": "red", "rotation": 3}]}, {"objects": [{"position": [109, 101, 113, 107], "class": "fish", "colour": "silver", "rotation": 0}, {"position": [35, 118, 39, 124], "class": "fish", "colour": "silver", "rotation": 0}, {"position": [49, 70, 53, 76], "class": "fish", "colour": "silver", "rotation": 2}, {"position": [68, 86, 74, 90], "class": "fish", "colour": "silver", "rotation": 1}, {"position": [100, 79, 106, 83], "class": "bag", "colour": "white", "rotation": 3}, {"position": [70, 45, 76, 49], "class": "bag", "colour": "white", "rotation": 3}, {"position": [18, 39, 24, 43], "class": "bag", "colour": "white", "rotation": 1}, {"position": [5, 114, 9, 120], "class": "bag", "colour": "white", "rotation": 0}, {"position": [36, 10, 42, 16], "class": "rock", "colour": "purple", "rotation": 0}, {"position": [4, 70, 10, 76], "class": "rock", "colour": "purple", "rotation": 0}, {"position": [80, 101, 86, 107], "class": "rock", "colour": "blue", "rotation": 0}, {"position": [103, 43, 113, 53], "class": "octopus", "colour": "red", "rotation": 3}]}, {"objects": [{"position": [109, 101, 113, 107], "class": "fish", "colour": "silver", "rotation": 0}, {"position": [35, 118, 39, 124], "class": "fish", "colour": "silver", "rotation": 0}, {"position": [49, 70, 53, 76], "class": "fish", "colour": "silver", "rotation": 2}, {"position": [68, 86, 74, 90], "class": "fish", "colour": "silver", "rotation": 1}, {"position": [100, 79, 106, 83], "class": "bag", "colour": "white", "rotation": 3}, {"position": [70, 45, 76, 49], "class": "bag", "colour": "white", "rotation": 3}, {"position": [18, 39, 24, 43], "class": "bag", "colour": "white", "rotation": 1}, {"position": [5, 114, 9, 120], "class": "bag", "colour": "white", "rotation": 0}, {"position": [36, 10, 42, 16], "class": "rock", "colour": "purple", "rotation": 0}, {"position": [4, 70, 10, 76], "class": "rock", "colour": "purple", "rotation": 0}, {"position": [80, 101, 86, 107], "class": "rock", "colour": "blue", "rotation": 0}, {"position": [91, 43, 101, 53], "class": "octopus", "colour": "red", "rotation": 3}]}, {"objects": [{"position": [109, 101, 113, 107], "class": "fish", "colour": "silver", "rotation": 0}, {"position": [35, 118, 39, 124], "class": "fish", "colour": "silver", "rotation": 0}, {"position": [49, 70, 53, 76], "class": "fish", "colour": "silver", "rotation": 2}, {"position": [68, 86, 74, 90], "class": "fish", "colour": "silver", "rotation": 1}, {"position": [100, 79, 106, 83], "class": "bag", "colour": "white", "rotation": 3}, {"position": [18, 39, 24, 43], "class": "bag", "colour": "white", "rotation": 1}, {"position": [5, 114, 9, 120], "class": "bag", "colour": "white", "rotation": 0}, {"position": [36, 10, 42, 16], "class": "rock", "colour": "purple", "rotation": 0}, {"position": [4, 70, 10, 76], "class": "rock", "colour": "purple", "rotation": 0}, {"position": [80, 101, 86, 107], "class": "rock", "colour": "blue", "rotation": 0}]}, {"objects": [{"position": [109, 101, 113, 107], "class": "fish", "colour": "silver", "rotation": 0}, {"position": [35, 118, 39, 124], "class": "fish", "colour": "silver", "rotation": 0}, {"position": [49, 70, 53, 76], "class": "fish", "colour": "silver", "rotation": 2}, {"position": [68, 86, 74, 90], "class": "fish", "colour": "silver", "rotation": 1}, {"position": [100, 79, 106, 83], "class": "bag", "colour": "white", "rotation": 3}, {"position": [18, 39, 24, 43], "class": "bag", "colour": "white", "rotation": 1}, {"position": [5, 114, 9, 120], "class": "bag", "colour": "white", "rotation": 0}, {"position": [36, 10, 42, 16], "class": "rock", "colour": "purple", "rotation": 0}, {"position": [4, 70, 10, 76], "class": "rock", "colour": "purple", "rotation": 0}, {"position": [80, 101, 86, 107], "class": "rock", "colour": "blue", "rotation": 0}]}, {"objects": [{"position": [109, 101, 113, 107], "class": "fish", "colour": "silver", "rotation": 0}, {"position": [35, 118, 39, 124], "class": "fish", "colour": "silver", "rotation": 0}, {"position": [49, 70, 53, 76], "class": "fish", "colour": "silver", "rotation": 2}, {"position": [68, 86, 74, 90], "class": "fish", "colour": "silver", "rotation": 1}, {"position": [100, 79, 106, 83], "class": "bag", "colour": "white", "rotation": 3}, {"position": [18, 39, 24, 43], "class": "bag", "colour": "white", "rotation": 1}, {"position": [5, 114, 9, 120], "class": "bag", "colour": "white", "rotation": 0}, {"position": [36, 10, 42, 16], "class": "rock", "colour": "purple", "rotation": 0}, {"position": [4, 70, 10, 76], "class": "rock", "colour": "purple", "rotation": 0}, {"position": [80, 101, 86, 107], "class": "rock", "colour": "blue", "rotation": 0}]}, {"objects": [{"position": [109, 101, 113, 107], "class": "fish", "colour": "silver", "rotation": 0}, {"position": [35, 118, 39, 124], "class": "fish", "colour": "silver", "rotation": 0}, {"position": [49, 70, 53, 76], "class": "fish", "colour": "silver", "rotation": 2}, {"position": [68, 86, 74, 90], "class": "fish", "colour": "silver", "rotation": 1}, {"position": [100, 79, 106, 83], "class": "bag", "colour": "white", "rotation": 3}, {"position": [18, 39, 24, 43], "class": "bag", "colour": "white", "rotation": 1}, {"position": [5, 114, 9, 120], "class": "bag", "colour": "white", "rotation": 0}, {"position": [36, 10, 42, 16], "class": "rock", "colour": "purple", "rotation": 0}, {"position": [4, 70, 10, 76], "class": "rock", "colour": "purple", "rotation": 0}, {"position": [80, 101, 86, 107], "class": "rock", "colour": "blue", "rotation": 0}]}, {"objects": [{"position": [109, 101, 113, 107], "class": "fish", "colour": "silver", "rotation": 0}, {"position": [35, 118, 39, 124], "class": "fish", "colour": "silver", "rotation": 0}, {"position": [49, 70, 53, 76], "class": "fish", "colour": "silver", "rotation": 2}, {"position": [68, 86, 74, 90], "class": "fish", "colour": "silver", "rotation": 1}, {"position": [100, 79, 106, 83], "class": "bag", "colour": "white", "rotation": 3}, {"position": [18, 39, 24, 43], "class": "bag", "colour": "white", "rotation": 1}, {"position": [5, 114, 9, 120], "class": "bag", "colour": "white", "rotation": 0}, {"position": [36, 10, 42, 16], "class": "rock", "colour": "purple", "rotation": 0}, {"position": [4, 70, 10, 76], "class": "rock", "colour": "purple", "rotation": 0}, {"position": [80, 101, 86, 107], "class": "rock", "colour": "blue", "rotation": 0}]}, {"objects": [{"position": [109, 101, 113, 107], "class": "fish", "colour": "silver", "rotation": 0}, {"position": [35, 118, 39, 124], "class": "fish", "colour": "silver", "rotation": 0}, {"position": [49, 70, 53, 76], "class": "fish", "colour": "silver", "rotation": 2}, {"position": [68, 86, 74, 90], "class": "fish", "colour": "silver", "rotation": 1}, {"position": [100, 79, 106, 83], "class": "bag", "colour": "white", "rotation": 3}, {"position": [18, 39, 24, 43], "class": "bag", "colour": "white", "rotation": 1}, {"position": [5, 114, 9, 120], "class": "bag", "colour": "white", "rotation": 0}, {"position": [36, 10, 42, 16], "class": "rock", "colour": "purple", "rotation": 0}, {"position": [4, 70, 10, 76], "class": "rock", "colour": "purple", "rotation": 0}, {"position": [80, 101, 86, 107], "class": "rock", "colour": "blue", "rotation": 0}]}, {"objects": [{"position": [109, 101, 113, 107], "class": "fish", "colour": "silver", "rotation": 0}, {"position": [35, 118, 39, 124], "class": "fish", "colour": "silver", "rotation": 0}, {"position": [49, 70, 53, 76], "class": "fish", "colour": "silver", "rotation": 2}, {"position": [68, 86, 74, 90], "class": "fish", "colour": "silver", "rotation": 1}, {"position": [100, 79, 106, 83], "class": "bag", "colour": "white", "rotation": 3}, {"position": [18, 39, 24, 43], "class": "bag", "colour": "white", "rotation": 1}, {"position": [5, 114, 9, 120], "class": "bag", "colour": "white", "rotation": 0}, {"position": [36, 10, 42, 16], "class": "rock", "colour": "purple", "rotation": 0}, {"position": [4, 70, 10, 76], "class": "rock", "colour": "purple", "rotation": 0}, {"position": [80, 101, 86, 107], "class": "rock", "colour": "blue", "rotation": 0}]}, {"objects": [{"position": [109, 101, 113, 107], "class": "fish", "colour": "silver", "rotation": 0}, {"position": [35, 118, 39, 124], "class": "fish", "colour": "silver", "rotation": 0}, {"position": [49, 70, 53, 76], "class": "fish", "colour": "silver", "rotation": 2}, {"position": [68, 86, 74, 90], "class": "fish", "colour": "silver", "rotation": 1}, {"position": [100, 79, 106, 83], "class": "bag", "colour": "white", "rotation": 3}, {"position": [18, 39, 24, 43], "class": "bag", "colour": "white", "rotation": 1}, {"position": [5, 114, 9, 120], "class": "bag", "colour": "white", "rotation": 0}, {"position": [36, 10, 42, 16], "class": "rock", "colour": "purple", "rotation": 0}, {"position": [4, 70, 10, 76], "class": "rock", "colour": "purple", "rotation": 0}, {"position": [80, 101, 86, 107], "class": "rock", "colour": "blue", "rotation": 0}]}, {"objects": [{"position": [109, 101, 113, 107], "class": "fish", "colour": "silver", "rotation": 0}, {"position": [35, 118, 39, 124], "class": "fish", "colour": "silver", "rotation": 0}, {"position": [49, 70, 53, 76], "class": "fish", "colour": "silver", "rotation": 2}, {"position": [68, 86, 74, 90], "class": "fish", "colour": "silver", "rotation": 1}, {"position": [100, 79, 106, 83], "class": "bag", "colour": "white", "rotation": 3}, {"position": [18, 39, 24, 43], "class": "bag", "colour": "white", "rotation": 1}, {"position": [5, 114, 9, 120], "class": "bag", "colour": "white", "rotation": 0}, {"position": [36, 10, 42, 16], "class": "rock", "colour": "purple", "rotation": 0}, {"position": [4, 70, 10, 76], "class": "rock", "colour": "purple", "rotation": 0}, {"position": [80, 101, 86, 107], "class": "rock", "colour": "blue", "rotation": 0}]}, {"objects": [{"position": [109, 101, 113, 107], "class": "fish", "colour": "silver", "rotation": 0}, {"position": [35, 118, 39, 124], "class": "fish", "colour": "silver", "rotation": 0}, {"position": [49, 70, 53, 76], "class": "fish", "colour": "silver", "rotation": 2}, {"position": [68, 86, 74, 90], "class": "fish", "colour": "silver", "rotation": 1}, {"position": [100, 79, 106, 83], "class": "bag", "colour": "white", "rotation": 3}, {"position": [18, 39, 24, 43], "class": "bag", "colour": "white", "rotation": 1}, {"position": [5, 114, 9, 120], "class": "bag", "colour": "white", "rotation": 0}, {"position": [36, 10, 42, 16], "class": "rock", "colour": "purple", "rotation": 0}, {"position": [4, 70, 10, 76], "class": "rock", "colour": "purple", "rotation": 0}, {"position": [80, 101, 86, 107], "class": "rock", "colour": "blue", "rotation": 0}]}, {"objects": [{"position": [109, 101, 113, 107], "class": "fish", "colour": "silver", "rotation": 0}, {"position": [35, 118, 39, 124], "class": "fish", "colour": "silver", "rotation": 0}, {"position": [49, 70, 53, 76], "class": "fish", "colour": "silver", "rotation": 2}, {"position": [68, 86, 74, 90], "class": "fish", "colour": "silver", "rotation": 1}, {"position": [100, 79, 106, 83], "class": "bag", "colour": "white", "rotation": 3}, {"position": [18, 39, 24, 43], "class": "bag", "colour": "white", "rotation": 1}, {"position": [5, 114, 9, 120], "class": "bag", "colour": "white", "rotation": 0}, {"position": [36, 10, 42, 16], "class": "rock", "colour": "purple", "rotation": 0}, {"position": [4, 70, 10, 76], "class": "rock", "colour": "purple", "rotation": 0}, {"position": [80, 101, 86, 107], "class": "rock", "colour": "blue", "rotation": 0}]}, {"objects": [{"position": [109, 101, 113, 107], "class": "fish", "colour": "silver", "rotation": 0}, {"position": [35, 118, 39, 124], "class": "fish", "colour": "silver", "rotation": 0}, {"position": [49, 70, 53, 76], "class": "fish", "colour": "silver", "rotation": 2}, {"position": [68, 86, 74, 90], "class": "fish", "colour": "silver", "rotation": 1}, {"position": [100, 79, 106, 83], "class": "bag", "colour": "white", "rotation": 3}, {"position": [18, 39, 24, 43], "class": "bag", "colour": "white", "rotation": 1}, {"position": [5, 114, 9, 120], "class": "bag", "colour": "white", "rotation": 0}, {"position": [36, 10, 42, 16], "class": "rock", "colour": "purple", "rotation": 0}, {"position": [4, 70, 10, 76], "class": "rock", "colour": "purple", "rotation": 0}, {"position": [80, 101, 86, 107], "class": "rock", "colour": "blue", "rotation": 0}]}, {"objects": [{"position": [109, 101, 113, 107], "class": "fish", "colour": "silver", "rotation": 0}, {"position": [35, 118, 39, 124], "class": "fish", "colour": "silver", "rotation": 0}, {"position": [49, 70, 53, 76], "class": "fish", "colour": "silver", "rotation": 2}, {"position": [68, 86, 74, 90], "class": "fish", "colour": "silver", "rotation": 1}, {"position": [100, 79, 106, 83], "class": "bag", "colour": "white", "rotation": 3}, {"position": [18, 39, 24, 43], "class": "bag", "colour": "white", "rotation": 1}, {"position": [5, 114, 9, 120], "class": "bag", "colour": "white", "rotation": 0}, {"position": [36, 10, 42, 16], "class": "rock", "colour": "purple", "rotation": 0}, {"position": [4, 70, 10, 76], "class": "rock", "colour": "purple", "rotation": 0}, {"position": [80, 101, 86, 107], "class": "rock", "colour": "blue", "rotation": 0}]}, {"objects": [{"position": [109, 101, 113, 107], "class": "fish", "colour": "silver", "rotation": 0}, {"position": [35, 118, 39, 124], "class": "fish", "colour": "silver", "rotation": 0}, {"position": [49, 70, 53, 76], "class": "fish", "colour": "silver", "rotation": 2}, {"position": [68, 86, 74, 90], "class": "fish", "colour": "silver", "rotation": 1}, {"position": [100, 79, 106, 83], "class": "bag", "colour": "white", "rotation": 3}, {"position": [18, 39, 24, 43], "class": "bag", "colour": "white", "rotation": 1}, {"position": [5, 114, 9, 120], "class": "bag", "colour": "white", "rotation": 0}, {"position": [36, 10, 42, 16], "class": "rock", "colour": "purple", "rotation": 0}, {"position": [4, 70, 10, 76], "class": "rock", "colour": "purple", "rotation": 0}, {"position": [80, 101, 86, 107], "class": "rock", "colour": "blue", "rotation": 0}]}, {"objects": [{"position": [109, 101, 113, 107], "class": "fish", "colour": "silver", "rotation": 0}, {"position": [35, 118, 39, 124], "class": "fish", "colour": "silver", "rotation": 0}, {"position": [49, 70, 53, 76], "class": "fish", "colour": "silver", "rotation": 2}, {"position": [68, 86, 74, 90], "class": "fish", "colour": "silver", "rotation": 1}, {"position": [100, 79, 106, 83], "class": "bag", "colour": "white", "rotation": 3}, {"position": [18, 39, 24, 43], "class": "bag", "colour": "white", "rotation": 1}, {"position": [5, 114, 9, 120], "class": "bag", "colour": "white", "rotation": 0}, {"position": [36, 10, 42, 16], "class": "rock", "colour": "purple", "rotation": 0}, {"position": [4, 70, 10, 76], "class": "rock", "colour": "purple", "rotation": 0}, {"position": [80, 101, 86, 107], "class": "rock", "colour": "blue", "rotation": 0}]}, {"objects": [{"position": [109, 101, 113, 107], "class": "fish", "colour": "silver", "rotation": 0}, {"position": [35, 118, 39, 124], "class": "fish", "colour": "silver", "rotation": 0}, {"position": [49, 70, 53, 76], "class": "fish", "colour": "silver", "rotation": 2}, {"position": [68, 86, 74, 90], "class": "fish", "colour": "silver", "rotation": 1}, {"position": [100, 79, 106, 83], "class": "bag", "colour": "white", "rotation": 3}, {"position": [18, 39, 24, 43], "class": "bag", "colour": "white", "rotation": 1}, {"position": [5, 114, 9, 120], "class": "bag", "colour": "white", "rotation": 0}, {"position": [36, 10, 42, 16], "class": "rock", "colour": "purple", "rotation": 0}, {"position": [4, 70, 10, 76], "class": "rock", "colour": "purple", "rotation": 0}, {"position": [80, 101, 86, 107], "class": "rock", "colour": "blue", "rotation": 0}]}, {"objects": [{"position": [109, 101, 113, 107], "class": "fish", "colour": "silver", "rotation": 0}, {"position": [35, 118, 39, 124], "class": "fish", "colour": "silver", "rotation": 0}, {"position": [49, 70, 53, 76], "class": "fish", "colour": "silver", "rotation": 2}, {"position": [68, 86, 74, 90], "class": "fish", "colour": "silver", "rotation": 1}, {"position": [100, 79, 106, 83], "class": "bag", "colour": "white", "rotation": 3}, {"position": [18, 39, 24, 43], "class": "bag", "colour": "white", "rotation": 1}, {"position": [5, 114, 9, 120], "class": "bag", "colour": "white", "rotation": 0}, {"position": [36, 10, 42, 16], "class": "rock", "colour": "purple", "rotation": 0}, {"position": [4, 70, 10, 76], "class": "rock", "colour": "purple", "rotation": 0}, {"position": [80, 101, 86, 107], "class": "rock", "colour": "blue", "rotation": 0}]}, {"objects": [{"position": [109, 101, 113, 107], "class": "fish", "colour": "silver", "rotation": 0}, {"position": [35, 118, 39, 124], "class": "fish", "colour": "silver", "rotation": 0}, {"position": [49, 70, 53, 76], "class": "fish", "colour": "silver", "rotation": 2}, {"position": [68, 86, 74, 90], "class": "fish", "colour": "silver", "rotation": 1}, {"position": [100, 79, 106, 83], "class": "bag", "colour": "white", "rotation": 3}, {"position": [18, 39, 24, 43], "class": "bag", "colour": "white", "rotation": 1}, {"position": [5, 114, 9, 120], "class": "bag", "colour": "white", "rotation": 0}, {"position": [36, 10, 42, 16], "class": "rock", "colour": "purple", "rotation": 0}, {"position": [4, 70, 10, 76], "class": "rock", "colour": "purple", "rotation": 0}, {"position": [80, 101, 86, 107], "class": "rock", "colour": "blue", "rotation": 0}]}, {"objects": [{"position": [109, 101, 113, 107], "class": "fish", "colour": "silver", "rotation": 0}, {"position": [35, 118, 39, 124], "class": "fish", "colour": "silver", "rotation": 0}, {"position": [49, 70, 53, 76], "class": "fish", "colour": "silver", "rotation": 2}, {"position": [68, 86, 74, 90], "class": "fish", "colour": "silver", "rotation": 1}, {"position": [100, 79, 106, 83], "class": "bag", "colour": "white", "rotation": 3}, {"position": [18, 39, 24, 43], "class": "bag", "colour": "white", "rotation": 1}, {"position": [5, 114, 9, 120], "class": "bag", "colour": "white", "rotation": 0}, {"position": [36, 10, 42, 16], "class": "rock", "colour": "purple", "rotation": 0}, {"position": [4, 70, 10, 76], "class": "rock", "colour": "purple", "rotation": 0}, {"position": [80, 101, 86, 107], "class": "rock", "colour": "blue", "rotation": 0}]}, {"objects": [{"position": [109, 101, 113, 107], "class": "fish", "colour": "silver", "rotation": 0}, {"position": [35, 118, 39, 124], "class": "fish", "colour": "silver", "rotation": 0}, {"position": [49, 70, 53, 76], "class": "fish", "colour": "silver", "rotation": 2}, {"position": [68, 86, 74, 90], "class": "fish", "colour": "silver", "rotation": 1}, {"position": [100, 79, 106, 83], "class": "bag", "colour": "white", "rotation": 3}, {"position": [18, 39, 24, 43], "class": "bag", "colour": "white", "rotation": 1}, {"position": [5, 114, 9, 120], "class": "bag", "colour": "white", "rotation": 0}, {"position": [36, 10, 42, 16], "class": "rock", "colour": "purple", "rotation": 0}, {"position": [4, 70, 10, 76], "class": "rock", "colour": "purple", "rotation": 0}, {"position": [80, 101, 86, 107], "class": "rock", "colour": "blue", "rotation": 0}]}, {"objects": [{"position": [109, 101, 113, 107], "class": "fish", "colour": "silver", "rotation": 0}, {"position": [35, 118, 39, 124], "class": "fish", "colour": "silver", "rotation": 0}, {"position": [49, 70, 53, 76], "class": "fish", "colour": "silver", "rotation": 2}, {"position": [68, 86, 74, 90], "class": "fish", "colour": "silver", "rotation": 1}, {"position": [100, 79, 106, 83], "class": "bag", "colour": "white", "rotation": 3}, {"position": [18, 39, 24, 43], "class": "bag", "colour": "white", "rotation": 1}, {"position": [5, 114, 9, 120], "class": "bag", "colour": "white", "rotation": 0}, {"position": [36, 10, 42, 16], "class": "rock", "colour": "purple", "rotation": 0}, {"position": [4, 70, 10, 76], "class": "rock", "colour": "purple", "rotation": 0}, {"position": [80, 101, 86, 107], "class": "rock", "colour": "blue", "rotation": 0}]}, {"objects": [{"position": [109, 101, 113, 107], "class": "fish", "colour": "silver", "rotation": 0}, {"position": [35, 118, 39, 124], "class": "fish", "colour": "silver", "rotation": 0}, {"position": [49, 70, 53, 76], "class": "fish", "colour": "silver", "rotation": 2}, {"position": [68, 86, 74, 90], "class": "fish", "colour": "silver", "rotation": 1}, {"position": [100, 79, 106, 83], "class": "bag", "colour": "white", "rotation": 3}, {"position": [18, 39, 24, 43], "class": "bag", "colour": "white", "rotation": 1}, {"position": [5, 114, 9, 120], "class": "bag", "colour": "white", "rotation": 0}, {"position": [36, 10, 42, 16], "class": "rock", "colour": "purple", "rotation": 0}, {"position": [4, 70, 10, 76], "class": "rock", "colour": "purple", "rotation": 0}, {"position": [80, 101, 86, 107], "class": "rock", "colour": "blue", "rotation": 0}]}, {"objects": [{"position": [109, 101, 113, 107], "class": "fish", "colour": "silver", "rotation": 0}, {"position": [35, 118, 39, 124], "class": "fish", "colour": "silver", "rotation": 0}, {"position": [49, 70, 53, 76], "class": "fish", "colour": "silver", "rotation": 2}, {"position": [68, 86, 74, 90], "class": "fish", "colour": "silver", "rotation": 1}, {"position": [100, 79, 106, 83], "class": "bag", "colour": "white", "rotation": 3}, {"position": [18, 39, 24, 43], "class": "bag", "colour": "white", "rotation": 1}, {"position": [5, 114, 9, 120], "class": "bag", "colour": "white", "rotation": 0}, {"position": [36, 10, 42, 16], "class": "rock", "colour": "purple", "rotation": 0}, {"position": [4, 70, 10, 76], "class": "rock", "colour": "purple", "rotation": 0}, {"position": [80, 101, 86, 107], "class": "rock", "colour": "blue", "rotation": 0}]}, {"objects": [{"position": [109, 101, 113, 107], "class": "fish", "colour": "silver", "rotation": 0}, {"position": [35, 118, 39, 124], "class": "fish", "colour": "silver", "rotation": 0}, {"position": [49, 70, 53, 76], "class": "fish", "colour": "silver", "rotation": 2}, {"position": [68, 86, 74, 90], "class": "fish", "colour": "silver", "rotation": 1}, {"position": [100, 79, 106, 83], "class": "bag", "colour": "white", "rotation": 3}, {"position": [18, 39, 24, 43], "class": "bag", "colour": "white", "rotation": 1}, {"position": [5, 114, 9, 120], "class": "bag", "colour": "white", "rotation": 0}, {"position": [36, 10, 42, 16], "class": "rock", "colour": "purple", "rotation": 0}, {"position": [4, 70, 10, 76], "class": "rock", "colour": "purple", "rotation": 0}, {"position": [80, 101, 86, 107], "class": "rock", "colour": "blue", "rotation": 0}]}, {"objects": [{"position": [109, 101, 113, 107], "class": "fish", "colour": "silver", "rotation": 0}, {"position": [35, 118, 39, 124], "class": "fish", "colour": "silver", "rotation": 0}, {"position": [49, 70, 53, 76], "class": "fish", "colour": "silver", "rotation": 2}, {"position": [68, 86, 74, 90], "class": "fish", "colour": "silver", "rotation": 1}, {"position": [100, 79, 106, 83], "class": "bag", "colour": "white", "rotation": 3}, {"position": [18, 39, 24, 43], "class": "bag", "colour": "white", "rotation": 1}, {"position": [5, 114, 9, 120], "class": "bag", "colour": "white", "rotation": 0}, {"position": [36, 10, 42, 16], "class": "rock", "colour": "purple", "rotation": 0}, {"position": [4, 70, 10, 76], "class": "rock", "colour": "purple", "rotation": 0}, {"position": [80, 101, 86, 107], "class": "rock", "colour": "blue", "rotation": 0}]}, {"objects": [{"position": [109, 101, 113, 107], "class": "fish", "colour": "silver", "rotation": 0}, {"position": [35, 118, 39, 124], "class": "fish", "colour": "silver", "rotation": 0}, {"position": [49, 70, 53, 76], "class": "fish", "colour": "silver", "rotation": 2}, {"position": [68, 86, 74, 90], "class": "fish", "colour": "silver", "rotation": 1}, {"position": [100, 79, 106, 83], "class": "bag", "colour": "white", "rotation": 3}, {"position": [18, 39, 24, 43], "class": "bag", "colour": "white", "rotation": 1}, {"position": [5, 114, 9, 120], "class": "bag", "colour": "white", "rotation": 0}, {"position": [36, 10, 42, 16], "class": "rock", "colour": "purple", "rotation": 0}, {"position": [4, 70, 10, 76], "class": "rock", "colour": "purple", "rotation": 0}, {"position": [80, 101, 86, 107], "class": "rock", "colour": "blue", "rotation": 0}]}], "events": [["move"], ["rotate"], ["rotate"], ["move"], ["move"], ["disappear", "move"], ["no event"], ["no event"], ["no event"], ["no event"], ["no event"], ["no event"], ["no event"], ["no event"], ["no event"], ["no event"], ["no event"], ["no event"], ["no event"], ["no event"], ["no event"], ["no event"], ["no event"], ["no event"], ["no event"], ["no event"], ["no event"], ["no event"], ["no event"], ["no event"], ["no event"]]}