{"frames": [{"objects": [{"position": [74, 120, 80, 124], "class": "fish", "colour": "silver", "rotation": 1}, {"position": [108, 84, 112, 90], "class": "fish", "colour": "silver", "rotation": 2}, {"position": [44, 24, 50, 28], "class": "bag", "colour": "white", "rotation": 1}, {"position": [80, 48, 84, 54], "class": "bag", "colour": "white", "rotation": 2}, {"position": [115, 110, 119, 116], "class": "bag", "colour": "white", "rotation": 2}, {"position": [21, 87, 27, 91], "class": "bag", "colour": "white", "rotation": 1}, {"position": [15, 41, 21, 47], "class": "rock", "colour": "brown", "rotation": 0}, {"position": [72, 16, 78, 22], "class": "rock", "colour": "blue", "rotation": 0}, {"position": [39, 77, 45, 83], "class": "rock", "colour": "brown", "rotation": 0}, {"position": [78, 69, 88, 79], "class": "octopus", "colour": "red", "rotation": 0}]}, {"objects": [{"position": [74, 120, 80, 124], "class": "fish", "colour": "silver", "rotation": 1}, {"position": [108, 84, 112, 90], "class": "fish", "colour": "silver", "rotation": 2}, {"position": [44, 24, 50, 28], "class": "bag", "colour": "white", "rotation": 1}, {"position": [80, 48, 84, 54], "class": "bag", "colour": "white", "rotation": 2}, {"position": [115, 110, 119, 116], "class": "bag", "colour": "white", "rotation": 2}, {"position": [21, 87, 27, 91], "class": "bag", "colour": "white", "rotation": 1}, {"position": [15, 41, 21, 47], "class": "rock", "colour": "brown", "rotation": 0}, {"position": [72, 16, 78, 22], "class": "rock", "colour": "blue", "rotation": 0}, {"position": [39, 77, 45, 83], "class": "rock", "colour": "brown", "rotation": 0}, {"position": [78, 69, 88, 79], "class": "octopus", "colour": "red", "rotation": 1}]}, {"objects": [{"position": [74, 120, 80, 124], "class": "fish", "colour": "silver", "rotation": 1}, {"position": [108, 84, 112, 90], "class": "fish", "colour": "silver", "rotation": 2}, {"position": [44, 24, 50, 28], "class": "bag", "colour": "white", "rotation": 1}, {"position": [80, 48, 84, 54], "class": "bag", "colour": "white", "rotation": 2}, {"position": [115, 110, 119, 116], "class": "bag", "colour": "white", "rotation": 2}, {"position": [21, 87, 27, 91], "class": "bag", "colour": "white", "rotation": 1}, {"position": [15, 41, 21, 47], "class": "rock", "colour": "brown", "rotation": 0}, {"position": [72, 16, 78, 22], "class": "rock", "colour": "blue", "rotation": 0}, {"position": [39, 77, 45, 83], "class": "rock", "colour": "brown", "rotation": 0}, {"position": [78, 69, 88, 79], "class": "octopus", "colour": "red", "rotation": 2}]}, {"objects": [{"position": [74, 120, 80, 124], "class": "fish", "colour": "silver", "rotation": 1}, {"position": [108, 84, 112, 90], "class": "fish", "colour": "silver", "rotation": 2}, {"position": [44, 24, 50, 28], "class": "bag", "colour": "white", "rotation": 1}, {"position": [80, 48, 84, 54], "class": "bag", "colour": "white", "rotation": 2}, {"position": [115, 110, 119, 116], "class": "bag", "colour": "white", "rotation": 2}, {"position": [21, 87, 27, 91], "class": "bag", "colour": "white", "rotation": 1}, {"position": [15, 41, 21, 47], "class": "rock", "colour": "brown", "rotation": 0}, {"position": [72, 16, 78, 22], "class": "rock", "colour": "blue", "rotation": 0}, {"position": [39, 77, 45, 83], "class": "rock", "colour": "brown", "rotation": 0}, {"position": [78, 81, 88, 91], "class": "octopus", "colour": "red", "rotation": 2}]}, {"objects": [{"position": [74, 120, 80, 124], "class": "fish", "colour": "silver", "rotation": 1}, {"position": [108, 84, 112, 90], "class": "fish", "colour": "silver", "rotation": 2}, {"position": [44, 24, 50, 28], "class": "bag", "colour": "white", "rotation": 1}, {"position": [80, 48, 84, 54], "class": "bag", "colour": "white", "rotation": 2}, {"position": [115, 110, 119, 116], "class": "bag", "colour": "white", "rotation": 2}, {"position": [21, 87, 27, 91], "class": "bag", "colour": "white", "rotation": 1}, {"position": [15, 41, 21, 47], "class": "rock", "colour": "brown", "rotation": 0}, {"position": [72, 16, 78, 22], "class": "rock", "colour": "blue", "rotation": 0}, {"position": [39, 77, 45, 83], "class": "rock", "colour": "brown", "rotation": 0}, {"position": [78, 93, 88, 103], "class": "octopus", "colour": "red", "rotation": 2}]}, {"objects": [{"position": [108, 84, 112, 90], "class": "fish", "colour": "silver", "rotation": 2}, {"position": [44, 24, 50, 28], "class": "bag", "colour": "white", "rotation": 1}, {"position": [80, 48, 84, 54], "class": "bag", "colour": "white", "rotation": 2}, {"position": [115, 110, 119, 116], "class": "bag", "colour": "white", "rotation": 2}, {"position": [21, 87, 27, 91], "class": "bag", "colour": "white", "rotation": 1}, {"position": [15, 41, 21, 47], "class": "rock", "colour": "brown", "rotation": 0}, {"position": [72, 16, 78, 22], "class": "rock", "colour": "blue", "rotation": 0}, {"position": [39, 77, 45, 83], "class": "rock", "colour": "brown", "rotation": 0}, {"position": [78, 105, 88, 115], "class": "octopus", "colour": "red", "rotation": 2}]}, {"objects": [{"position": [108, 84, 112, 90], "class": "fish", "colour": "silver", "rotation": 2}, {"position": [44, 24, 50, 28], "class": "bag", "colour": "white", "rotation": 1}, {"position": [80, 48, 84, 54], "class": "bag", "colour": "white", "rotation": 2}, {"position": [115, 110, 119, 116], "class": "bag", "colour": "white", "rotation": 2}, {"position": [21, 87, 27, 91], "class": "bag", "colour": "white", "rotation": 1}, {"position": [15, 41, 21, 47], "class": "rock", "colour": "brown", "rotation": 0}, {"position": [72, 16, 78, 22], "class": "rock", "colour": "blue", "rotation": 0}, {"position": [39, 77, 45, 83], "class": "rock", "colour": "brown", "rotation": 0}, {"position": [78, 117, 88, 127], "class": "octopus", "colour": "red", "rotation": 2}]}, {"objects": [{"position": [108, 84, 112, 90], "class": "fish", "colour": "silver", "rotation": 2}, {"position": [44, 24, 50, 28], "class": "bag", "colour": "white", "rotation": 1}, {"position": [80, 48, 84, 54], "class": "bag", "colour": "white", "rotation": 2}, {"position": [115, 110, 119, 116], "class": "bag", "colour": "white", "rotation": 2}, {"position": [21, 87, 27, 91], "class": "bag", "colour": "white", "rotation": 1}, {"position": [15, 41, 21, 47], "class": "rock", "colour": "brown", "rotation": 0}, {"position": [72, 16, 78, 22], "class": "rock", "colour": "blue", "rotation": 0}, {"position": [39, 77, 45, 83], "class": "rock", "colour": "brown", "rotation": 0}, {"position": [78, 117, 88, 127], "class": "octopus", "colour": "red", "rotation": 1}]}, {"objects": [{"position": [108, 84, 112, 90], "class": "fish", "colour": "silver", "rotation": 2}, {"position": [44, 24, 50, 28], "class": "bag", "colour": "white", "rotation": 1}, {"position": [80, 48, 84, 54], "class": "bag", "colour": "white", "rotation": 2}, {"position": [115, 110, 119, 116], "class": "bag", "colour": "white", "rotation": 2}, {"position": [21, 87, 27, 91], "class": "bag", "colour": "white", "rotation": 1}, {"position": [15, 41, 21, 47], "class": "rock", "colour": "brown", "rotation": 0}, {"position": [72, 16, 78, 22], "class": "rock", "colour": "blue", "rotation": 0}, {"position": [39, 77, 45, 83], "class": "rock", "colour": "brown", "rotation": 0}, {"position": [78, 117, 88, 127], "class": "octopus", "colour": "red", "rotation": 2}]}, {"objects": [{"position": [108, 84, 112, 90], "class": "fish", "colour": "silver", "rotation": 2}, {"position": [44, 24, 50, 28], "class": "bag", "colour": "white", "rotation": 1}, {"position": [80, 48, 84, 54], "class": "bag", "colour": "white", "rotation": 2}, {"position": [115, 110, 119, 116], "class": "bag", "colour": "white", "rotation": 2}, {"position": [21, 87, 27, 91], "class": "bag", "colour": "white", "rotation": 1}, {"position": [15, 41, 21, 47], "class": "rock", "colour": "brown", "rotation": 0}, {"position": [72, 16, 78, 22], "class": "rock", "colour": "blue", "rotation": 0}, {"position": [39, 77, 45, 83], "class": "rock", "colour": "brown", "rotation": 0}, {"position": [78, 117, 88, 127], "class": "octopus", "colour": "red", "rotation": 3}]}, {"objects": [{"position": [108, 84, 112, 90], "class": "fish", "colour": "silver", "rotation": 2}, {"position": [44, 24, 50, 28], "class": "bag", "colour": "white", "rotation": 1}, {"position": [80, 48, 84, 54], "class": "bag", "colour": "white", "rotation": 2}, {"position": [115, 110, 119, 116], "class": "bag", "colour": "white", "rotation": 2}, {"position": [21, 87, 27, 91], "class": "bag", "colour": "white", "rotation": 1}, {"position": [15, 41, 21, 47], "class": "rock", "colour": "brown", "rotation": 0}, {"position": [72, 16, 78, 22], "class": "rock", "colour": "blue", "rotation": 0}, {"position": [39, 77, 45, 83], "class": "rock", "colour": "brown", "rotation": 0}, {"position": [78, 117, 88, 127], "class": "octopus", "colour": "red", "rotation": 2}]}, {"objects": [{"position": [108, 84, 112, 90], "class": "fish", "colour": "silver", "rotation": 2}, {"position": [44, 24, 50, 28], "class": "bag", "colour": "white", "rotation": 1}, {"position": [80, 48, 84, 54], "class": "bag", "colour": "white", "rotation": 2}, {"position": [115, 110, 119, 116], "class": "bag", "colour": "white", "rotation": 2}, {"position": [21, 87, 27, 91], "class": "bag", "colour": "white", "rotation": 1}, {"position": [15, 41, 21, 47], "class": "rock", "colour": "brown", "rotation": 0}, {"position": [72, 16, 78, 22], "class": "rock", "colour": "blue", "rotation": 0}, {"position": [39, 77, 45, 83], "class": "rock", "colour": "brown", "rotation": 0}, {"position": [78, 117, 88, 127], "class": "octopus", "colour": "red", "rotation": 3}]}, {"objects": [{"position": [108, 84, 112, 90], "class": "fish", "colour": "silver", "rotation": 2}, {"position": [44, 24, 50, 28], "class": "bag", "colour": "white", "rotation": 1}, {"position": [80, 48, 84, 54], "class": "bag", "colour": "white", "rotation": 2}, {"position": [115, 110, 119, 116], "class": "bag", "colour": "white", "rotation": 2}, {"position": [21, 87, 27, 91], "class": "bag", "colour": "white", "rotation": 1}, {"position": [15, 41, 21, 47], "class": "rock", "colour": "brown", "rotation": 0}, {"position": [72, 16, 78, 22], "class": "rock", "colour": "blue", "rotation": 0}, {"position": [39, 77, 45, 83], "class": "rock", "colour": "brown", "rotation": 0}, {"position": [66, 117, 76, 127], "class": "octopus", "colour": "red", "rotation": 3}]}, {"objects": [{"position": [108, 84, 112, 90], "class": "fish", "colour": "silver", "rotation": 2}, {"position": [44, 24, 50, 28], "class": "bag", "colour": "white", "rotation": 1}, {"position": [80, 48, 84, 54], "class": "bag", "colour": "white", "rotation": 2}, {"position": [115, 110, 119, 116], "class": "bag", "colour": "white", "rotation": 2}, {"position": [21, 87, 27, 91], "class": "bag", "colour": "white", "rotation": 1}, {"position": [15, 41, 21, 47], "class": "rock", "colour": "brown", "rotation": 0}, {"position": [72, 16, 78, 22], "class": "rock", "colour": "blue", "rotation": 0}, {"position": [39, 77, 45, 83], "class": "rock", "colour": "brown", "rotation": 0}, {"position": [54, 117, 64, 127], "class": "octopus", "colour": "red", "rotation": 3}]}, {"objects": [{"position": [108, 84, 112, 90], "class": "fish", "colour": "silver", "rotation": 2}, {"position": [44, 24, 50, 28], "class": "bag", "colour": "white", "rotation": 1}, {"position": [80, 48, 84, 54], "class": "bag", "colour": "white", "rotation": 2}, {"position": [115, 110, 119, 116], "class": "bag", "colour": "white", "rotation": 2}, {"position": [21, 87, 27, 91], "class": "bag", "colour": "white", "rotation": 1}, {"position": [15, 41, 21, 47], "class": "rock", "colour": "brown", "rotation": 0}, {"position": [72, 16, 78, 22], "class": "rock", "colour": "blue", "rotation": 0}, {"position": [39, 77, 45, 83], "class": "rock", "colour": "brown", "rotation": 0}, {"position": [54, 117, 64, 127], "class": "octopus", "colour": "red", "rotation": 0}]}, {"objects": [{"position": [108, 84, 112, 90], "class": "fish", "colour": "silver", "rotation": 2}, {"position": [44, 24, 50, 28], "class": "bag", "colour": "white", "rotation": 1}, {"position": [80, 48, 84, 54], "class": "bag", "colour": "white", "rotation": 2}, {"position": [115, 110, 119, 116], "class": "bag", "colour": "white", "rotation": 2}, {"position": [21, 87, 27, 91], "class": "bag", "colour": "white", "rotation": 1}, {"position": [15, 41, 21, 47], "class": "rock", "colour": "brown", "rotation": 0}, {"position": [72, 16, 78, 22], "class": "rock", "colour": "blue", "rotation": 0}, {"position": [39, 77, 45, 83], "class": "rock", "colour": "brown", "rotation": 0}, {"position": [54, 105, 64, 115], "class": "octopus", "colour": "red", "rotation": 0}]}, {"objects": [{"position": [108, 84, 112, 90], "class": "fish", "colour": "silver", "rotation": 2}, {"position": [44, 24, 50, 28], "class": "bag", "colour": "white", "rotation": 1}, {"position": [80, 48, 84, 54], "class": "bag", "colour": "white", "rotation": 2}, {"position": [115, 110, 119, 116], "class": "bag", "colour": "white", "rotation": 2}, {"position": [21, 87, 27, 91], "class": "bag", "colour": "white", "rotation": 1}, {"position": [15, 41, 21, 47], "class": "rock", "colour": "brown", "rotation": 0}, {"position": [72, 16, 78, 22], "class": "rock", "colour": "blue", "rotation": 0}, {"position": [39, 77, 45, 83], "class": "rock", "colour": "brown", "rotation": 0}, {"position": [54, 93, 64, 103], "class": "octopus", "colour": "red", "rotation": 0}]}, {"objects": [{"position": [108, 84, 112, 90], "class": "fish", "colour": "silver", "rotation": 2}, {"position": [44, 24, 50, 28], "class": "bag", "colour": "white", "rotation": 1}, {"position": [80, 48, 84, 54], "class": "bag", "colour": "white", "rotation": 2}, {"position": [115, 110, 119, 116], "class": "bag", "colour": "white", "rotation": 2}, {"position": [21, 87, 27, 91], "class": "bag", "colour": "white", "rotation": 1}, {"position": [15, 41, 21, 47], "class": "rock", "colour": "brown", "rotation": 0}, {"position": [72, 16, 78, 22], "class": "rock", "colour": "blue", "rotation": 0}, {"position": [39, 77, 45, 83], "class": "rock", "colour": "brown", "rotation": 0}, {"position": [54, 81, 64, 91], "class": "octopus", "colour": "red", "rotation": 0}]}, {"objects": [{"position": [108, 84, 112, 90], "class": "fish", "colour": "silver", "rotation": 2}, {"position": [44, 24, 50, 28], "class": "bag", "colour": "white", "rotation": 1}, {"position": [80, 48, 84, 54], "class": "bag", "colour": "white", "rotation": 2}, {"position": [115, 110, 119, 116], "class": "bag", "colour": "white", "rotation": 2}, {"position": [21, 87, 27, 91], "class": "bag", "colour": "white", "rotation": 1}, {"position": [15, 41, 21, 47], "class": "rock", "colour": "brown", "rotation": 0}, {"position": [72, 16, 78, 22], "class": "rock", "colour": "blue", "rotation": 0}, {"position": [39, 77, 45, 83], "class": "rock", "colour": "brown", "rotation": 0}, {"position": [54, 69, 64, 79], "class": "octopus", "colour": "red", "rotation": 0}]}, {"objects": [{"position": [108, 84, 112, 90], "class": "fish", "colour": "silver", "rotation": 2}, {"position": [44, 24, 50, 28], "class": "bag", "colour": "white", "rotation": 1}, {"position": [80, 48, 84, 54], "class": "bag", "colour": "white", "rotation": 2}, {"position": [115, 110, 119, 116], "class": "bag", "colour": "white", "rotation": 2}, {"position": [21, 87, 27, 91], "class": "bag", "colour": "white", "rotation": 1}, {"position": [15, 41, 21, 47], "class": "rock", "colour": "brown", "rotation": 0}, {"position": [72, 16, 78, 22], "class": "rock", "colour": "blue", "rotation": 0}, {"position": [39, 77, 45, 83], "class": "rock", "colour": "brown", "rotation": 0}, {"position": [54, 57, 64, 67], "class": "octopus", "colour": "red", "rotation": 0}]}, {"objects": [{"position": [108, 84, 112, 90], "class": "fish", "colour": "silver", "rotation": 2}, {"position": [44, 24, 50, 28], "class": "bag", "colour": "white", "rotation": 1}, {"position": [80, 48, 84, 54], "class": "bag", "colour": "white", "rotation": 2}, {"position": [115, 110, 119, 116], "class": "bag", "colour": "white", "rotation": 2}, {"position": [21, 87, 27, 91], "class": "bag", "colour": "white", "rotation": 1}, {"position": [15, 41, 21, 47], "class": "rock", "colour": "brown", "rotation": 0}, {"position": [72, 16, 78, 22], "class": "rock", "colour": "blue", "rotation": 0}, {"position": [39, 77, 45, 83], "class": "rock", "colour": "brown", "rotation": 0}, {"position": [54, 57, 64, 67], "class": "octopus", "colour": "red", "rotation": 1}]}, {"objects": [{"position": [108, 84, 112, 90], "class": "fish", "colour": "silver", "rotation": 2}, {"position": [44, 24, 50, 28], "class": "bag", "colour": "white", "rotation": 1}, {"position": [115, 110, 119, 116], "class": "bag", "colour": "white", "rotation": 2}, {"position": [21, 87, 27, 91], "class": "bag", "colour": "white", "rotation": 1}, {"position": [15, 41, 21, 47], "class": "rock", "colour": "brown", "rotation": 0}, {"position": [72, 16, 78, 22], "class": "rock", "colour": "blue", "rotation": 0}, {"position": [39, 77, 45, 83], "class": "rock", "colour": "brown", "rotation": 0}]}, {"objects": [{"position": [108, 84, 112, 90], "class": "fish", "colour": "silver", "rotation": 2}, {"position": [44, 24, 50, 28], "class": "bag", "colour": "white", "rotation": 1}, {"position": [115, 110, 119, 116], "class": "bag", "colour": "white", "rotation": 2}, {"position": [21, 87, 27, 91], "class": "bag", "colour": "white", "rotation": 1}, {"position": [15, 41, 21, 47], "class": "rock", "colour": "brown", "rotation": 0}, {"position": [72, 16, 78, 22], "class": "rock", "colour": "blue", "rotation": 0}, {"position": [39, 77, 45, 83], "class": "rock", "colour": "brown", "rotation": 0}]}, {"objects": [{"position": [108, 84, 112, 90], "class": "fish", "colour": "silver", "rotation": 2}, {"position": [44, 24, 50, 28], "class": "bag", "colour": "white", "rotation": 1}, {"position": [115, 110, 119, 116], "class": "bag", "colour": "white", "rotation": 2}, {"position": [21, 87, 27, 91], "class": "bag", "colour": "white", "rotation": 1}, {"position": [15, 41, 21, 47], "class": "rock", "colour": "brown", "rotation": 0}, {"position": [72, 16, 78, 22], "class": "rock", "colour": "blue", "rotation": 0}, {"position": [39, 77, 45, 83], "class": "rock", "colour": "brown", "rotation": 0}]}, {"objects": [{"position": [108, 84, 112, 90], "class": "fish", "colour": "silver", "rotation": 2}, {"position": [44, 24, 50, 28], "class": "bag", "colour": "white", "rotation": 1}, {"position": [115, 110, 119, 116], "class": "bag", "colour": "white", "rotation": 2}, {"position": [21, 87, 27, 91], "class": "bag", "colour": "white", "rotation": 1}, {"position": [15, 41, 21, 47], "class": "rock", "colour": "brown", "rotation": 0}, {"position": [72, 16, 78, 22], "class": "rock", "colour": "blue", "rotation": 0}, {"position": [39, 77, 45, 83], "class": "rock", "colour": "brown", "rotation": 0}]}, {"objects": [{"position": [108, 84, 112, 90], "class": "fish", "colour": "silver", "rotation": 2}, {"position": [44, 24, 50, 28], "class": "bag", "colour": "white", "rotation": 1}, {"position": [115, 110, 119, 116], "class": "bag", "colour": "white", "rotation": 2}, {"position": [21, 87, 27, 91], "class": "bag", "colour": "white", "rotation": 1}, {"position": [15, 41, 21, 47], "class": "rock", "colour": "brown", "rotation": 0}, {"position": [72, 16, 78, 22], "class": "rock", "colour": "blue", "rotation": 0}, {"position": [39, 77, 45, 83], "class": "rock", "colour": "brown", "rotation": 0}]}, {"objects": [{"position": [108, 84, 112, 90], "class": "fish", "colour": "silver", "rotation": 2}, {"position": [44, 24, 50, 28], "class": "bag", "colour": "white", "rotation": 1}, {"position": [115, 110, 119, 116], "class": "bag", "colour": "white", "rotation": 2}, {"position": [21, 87, 27, 91], "class": "bag", "colour": "white", "rotation": 1}, {"position": [15, 41, 21, 47], "class": "rock", "colour": "brown", "rotation": 0}, {"position": [72, 16, 78, 22], "class": "rock", "colour": "blue", "rotation": 0}, {"position": [39, 77, 45, 83], "class": "rock", "colour": "brown", "rotation": 0}]}, {"objects": [{"position": [108, 84, 112, 90], "class": "fish", "colour": "silver", "rotation": 2}, {"position": [44, 24, 50, 28], "class": "bag", "colour": "white", "rotation": 1}, {"position": [115, 110, 119, 116], "class": "bag", "colour": "white", "rotation": 2}, {"position": [21, 87, 27, 91], "class": "bag", "colour": "white", "rotation": 1}, {"position": [15, 41, 21, 47], "class": "rock", "colour": "brown", "rotation": 0}, {"position": [72, 16, 78, 22], "class": "rock", "colour": "blue", "rotation": 0}, {"position": [39, 77, 45, 83], "class": "rock", "colour": "brown", "rotation": 0}]}, {"objects": [{"position": [108, 84, 112, 90], "class": "fish", "colour": "silver", "rotation": 2}, {"position": [44, 24, 50, 28], "class": "bag", "colour": "white", "rotation": 1}, {"position": [115, 110, 119, 116], "class": "bag", "colour": "white", "rotation": 2}, {"position": [21, 87, 27, 91], "class": "bag", "colour": "white", "rotation": 1}, {"position": [15, 41, 21, 47], "class": "rock", "colour": "brown", "rotation": 0}, {"position": [72, 16, 78, 22], "class": "rock", "colour": "blue", "rotation": 0}, {"position": [39, 77, 45, 83], "class": "rock", "colour": "brown", "rotation": 0}]}, {"objects": [{"position": [108, 84, 112, 90], "class": "fish", "colour": "silver", "rotation": 2}, {"position": [44, 24, 50, 28], "class": "bag", "colour": "white", "rotation": 1}, {"position": [115, 110, 119, 116], "class": "bag", "colour": "white", "rotation": 2}, {"position": [21, 87, 27, 91], "class": "bag", "colour": "white", "rotation": 1}, {"position": [15, 41, 21, 47], "class": "rock", "colour": "brown", "rotation": 0}, {"position": [72, 16, 78, 22], "class": "rock", "colour": "blue", "rotation": 0}, {"position": [39, 77, 45, 83], "class": "rock", "colour": "brown", "rotation": 0}]}, {"objects": [{"position": [108, 84, 112, 90], "class": "fish", "colour": "silver", "rotation": 2}, {"position": [44, 24, 50, 28], "class": "bag", "colour": "white", "rotation": 1}, {"position": [115, 110, 119, 116], "class": "bag", "colour": "white", "rotation": 2}, {"position": [21, 87, 27, 91], "class": "bag", "colour": "white", "rotation": 1}, {"position": [15, 41, 21, 47], "class": "rock", "colour": "brown", "rotation": 0}, {"position": [72, 16, 78, 22], "class": "rock", "colour": "blue", "rotation": 0}, {"position": [39, 77, 45, 83], "class": "rock", "colour": "brown", "rotation": 0}]}, {"objects": [{"position": [108, 84, 112, 90], "class": "fish", "colour": "silver", "rotation": 2}, {"position": [44, 24, 50, 28], "class": "bag", "colour": "white", "rotation": 1}, {"position": [115, 110, 119, 116], "class": "bag", "colour": "white", "rotation": 2}, {"position": [21, 87, 27, 91], "class": "bag", "colour": "white", "rotation": 1}, {"position": [15, 41, 21, 47], "class": "rock", "colour": "brown", "rotation": 0}, {"position": [72, 16, 78, 22], "class": "rock", "colour": "blue", "rotation": 0}, {"position": [39, 77, 45, 83], "class": "rock", "colour": "brown", "rotation": 0}]}], "events": [["rotate"], ["rotate"], ["move"], ["move"], ["disappear", "move"], ["move"], ["rotate"], ["rotate"], ["rotate"], ["rotate"], ["rotate"], ["move"], ["move"], ["rotate"], ["move"], ["move"], ["move"], ["move"], ["move"], ["rotate"], ["disappear", "move"], ["no event"], ["no event"], ["no event"], ["no event"], ["no event"], ["no event"], ["no event"], ["no event"], ["no event"], ["no event"]]}